yamtimes/__init__.py
yamtimes/yamtimes.py
yamtimes-0.0.1.dist-info/METADATA
yamtimes-0.0.1.dist-info/WHEEL
yamtimes-0.0.1.dist-info/top_level.txt
yamtimes-0.0.1.dist-info/RECORD
