Metadata-Version: 2.1
Name: yamtimes
Version: 0.0.1
Summary: Modern Date and Time Handling library for Python
Home-page: https://github.com/svidaniya/yamtimes
Author: svidaniya
Author-email: svidaniyafg@gmail.com
Classifier: Programming Language :: Python :: 3
Classifier: License :: OSI Approved :: MIT License
Classifier: Operating System :: OS Independent
Requires-Python: >=3.6
Requires-Dist: python-dateutil==2.9.0.post0
Requires-Dist: six==1.17.0
